clarus/__init__.py
clarus/api.py
clarus/api_config.py
clarus/models.py
clarus/output_types.py
clarus/resource_util.py
clarus/services/__init__.py
clarus/services/ccp.py
clarus/services/compliance.py
clarus/services/credit.py
clarus/services/custom.py
clarus/services/dates.py
clarus/services/etd.py
clarus/services/frtb.py
clarus/services/hedge.py
clarus/services/load.py
clarus/services/margin.py
clarus/services/market.py
clarus/services/portfolio.py
clarus/services/profitloss.py
clarus/services/risk.py
clarus/services/sdr.py
clarus/services/simm.py
clarus/services/trade.py
clarus/services/util.py
clarus/services/xva.py
clarus_beta-0.1.30b11.dist-info/DESCRIPTION.rst
clarus_beta-0.1.30b11.dist-info/METADATA
clarus_beta-0.1.30b11.dist-info/RECORD
clarus_beta-0.1.30b11.dist-info/WHEEL
clarus_beta-0.1.30b11.dist-info/metadata.json
clarus_beta-0.1.30b11.dist-info/top_level.txt
clarusx/__init__.py
