Metadata-Version: 2.0
Name: clarus-beta
Version: 0.1.30b11
Summary: Clarus Microservices
Home-page: http://www.clarusft.com
Author: Clarus Financial Technology
Author-email: support@clarusft.com
License: UNKNOWN
Platform: UNKNOWN
Requires-Dist: requests
Requires-Dist: six
